[
  {
    "quote": "If debugging is the process of removing software bugs, then programming must be the process of putting them in.",
    "author": "Edsger W. Dijkstra",
    "description": "creator of the Dijkstra pathfinding algothrim"
  },
  {
    "quote": "Any application that can be written in Javascript, will eventually be written in Javascript.",
    "author": "Jeff Atwood",
    "description": "creator of Stack Overflow"
  },
  {
    "quote": "There are only two kinds of languages: the ones people complain about and the ones nobody uses.",
    "author": "Bjarne Stroustrup",
    "description": "creator of C++"
  },
  {
    "quote": "C++ is such a bad language!",
    "author": "Linus Torvalds",
    "description": "creator of Linux and Git"
  }
]
